alphastation/__init__.py
alphastation/core.py
alphastation-0.1.0.dist-info/licenses/LICENSE
alphastation-0.1.0.dist-info/METADATA
alphastation-0.1.0.dist-info/WHEEL
alphastation-0.1.0.dist-info/top_level.txt
alphastation-0.1.0.dist-info/RECORD
