Metadata-Version: 2.4
Name: alphastation
Version: 0.1.0
Summary: AlphaStation - A minimal placeholder Python package
Author-email: AlphaStation <alphastation@example.com>
License: MIT
Project-URL: Homepage, https://github.com/alphastation/alphastation
Keywords: alphastation,placeholder
Classifier: Development Status :: 3 - Alpha
Classifier: Intended Audience :: Developers
Classifier: License :: OSI Approved :: MIT License
Classifier: Operating System :: OS Independent
Classifier: Programming Language :: Python :: 3
Classifier: Programming Language :: Python :: 3.7
Classifier: Programming Language :: Python :: 3.8
Classifier: Programming Language :: Python :: 3.9
Classifier: Programming Language :: Python :: 3.10
Classifier: Programming Language :: Python :: 3.11
Requires-Python: >=3.7
License-File: LICENSE
Dynamic: license-file
